coinpy/Binomialdistribution.py
coinpy/Gaussiandistribution.py
coinpy/Generaldistribution.py
coinpy/__init__.py
coinpy-1.1.dist-info/METADATA
coinpy-1.1.dist-info/WHEEL
coinpy-1.1.dist-info/top_level.txt
coinpy-1.1.dist-info/RECORD
