Metadata-Version: 2.1
Name: coinpy
Version: 1.1
Summary: Gaussian distributions
Home-page: https://github.com/feeblefruits/coinpy
Author: Jacques Coetzee
Author-email: j.coetzee0@gmail.com
License: MIT
Platform: UNKNOWN
